mgrc/__init__.py
mgrc/help.py
mgrc/t.py
mgrc-1.0.7.dist-info/LICENSE
mgrc-1.0.7.dist-info/METADATA
mgrc-1.0.7.dist-info/WHEEL
mgrc-1.0.7.dist-info/top_level.txt
mgrc-1.0.7.dist-info/RECORD
