Metadata-Version: 2.1
Name: mgrc
Version: 1.0.7
Summary: Junior-level package. A small, set of modules package. Developer tools; the syntax is in the programming language, python3.10.
Author-email: Richard Craddock <yerbro@gmail.com>
Project-URL: Homepage, https://helpwithcode.w3spaces.com/mgrc_t.txt
Project-URL: url, https://helpwithcode.w3spaces.com/mgrc_help.txt
Classifier: Programming Language :: Python :: 3.10
Classifier: License :: Free For Home Use
Classifier: Topic :: System :: Operating System Kernels :: Linux
Requires-Python: >=3.10
License-File: LICENSE
